nonebot_plugin_avalon-0.2.2.dist-info/METADATA
nonebot_plugin_avalon-0.2.2.dist-info/WHEEL
nonebot_plugin_avalon-0.2.2.dist-info/licenses/LICENSE
nonebot_plugin_avalon/__init__.py
nonebot_plugin_avalon/game/__init__.py
nonebot_plugin_avalon/game/game.py
nonebot_plugin_avalon/game/role.py
nonebot_plugin_avalon/game/round.py
nonebot_plugin_avalon/game/state.py
nonebot_plugin_avalon/game/state_machine.py
nonebot_plugin_avalon/game/states/__init__.py
nonebot_plugin_avalon/game/states/assassinate.py
nonebot_plugin_avalon/game/states/force_end.py
nonebot_plugin_avalon/game/states/game_end.py
nonebot_plugin_avalon/game/states/initialize.py
nonebot_plugin_avalon/game/states/next_leader.py
nonebot_plugin_avalon/game/states/team_build.py
nonebot_plugin_avalon/game/states/team_set_out.py
nonebot_plugin_avalon/game/states/team_vote.py
nonebot_plugin_avalon/game/states/wait_start.py
nonebot_plugin_avalon/matchers.py
nonebot_plugin_avalon-0.2.2.dist-info/RECORD
