Metadata-Version: 2.1
Name: nonebot-plugin-avalon
Version: 0.2.2
Summary: Avalon game plugin for nonebot2
Author-Email: SNRainiar <rainiar@foxmail.com>
License: AGPL-3.0-or-later
Classifier: Programming Language :: Python :: 3
Classifier: License :: OSI Approved :: GNU Affero General Public License v3 or later (AGPLv3+)
Classifier: Operating System :: OS Independent
Project-URL: Homepage, https://github.com/SamuNatsu/nonebot-plugin-avalon
Project-URL: Issues, https://github.com/SamuNatsu/nonebot-plugin-avalon/issues
Requires-Python: >=3.10
Requires-Dist: nonebot-plugin-alconna>=0.51.1
Requires-Dist: nonebot-plugin-session>=0.3.2
Requires-Dist: nonebot-plugin-apscheduler>=0.5.0
Requires-Dist: nonebot-plugin-userinfo>=0.2.5
Requires-Dist: nonebot2>=2.3.3
